docs_src/conf.py
docs_src/generatePages.py
psychopy_bbtk/__init__.py
psychopy_bbtk/forcePad.py
psychopy_bbtk/tpad.py
psychopy_bbtk/components/tpad.py
psychopy_bbtk-0.0.14.dist-info/licenses/LICENSE
tests/__init__.py
tests/test_builder/__init__.py
tests/test_coder/__init__.py
tests/test_coder/test_running_via_liaison.py
psychopy_bbtk-0.0.14.dist-info/METADATA
psychopy_bbtk-0.0.14.dist-info/WHEEL
psychopy_bbtk-0.0.14.dist-info/entry_points.txt
psychopy_bbtk-0.0.14.dist-info/top_level.txt
psychopy_bbtk-0.0.14.dist-info/RECORD
