Metadata-Version: 2.4
Name: psychopy-bbtk
Version: 0.0.14
Summary: Extension package for adding support for BlackBoxToolkit devices to PsychoPy.
Author-email: Jon Peirce <jon@opensceincetools.org>, Matthew Cutone <mcutone@opensceincetools.org>
License: GNU General Public License v3 (GPLv3)
Project-URL: homepage, https://github.com/psychopy/psychopy-bbtk
Project-URL: changelog, https://github.com/psychopy/psychopy-bbtk/blob/main/CHANGELOG.txt
Project-URL: documentation, https://pages.github.com/psychopy/psychopy-bbtk
Project-URL: repository, https://github.com/psychopy/psychopy-bbtk
Classifier: License :: OSI Approved :: GNU General Public License v3 (GPLv3)
Classifier: Programming Language :: Python :: 3
Classifier: Programming Language :: Python :: 3 :: Only
Classifier: Programming Language :: Python :: 3.7
Classifier: Programming Language :: Python :: 3.8
Classifier: Programming Language :: Python :: 3.9
Classifier: Programming Language :: Python :: 3.10
Classifier: Programming Language :: Python :: 3.11
Classifier: Programming Language :: Python :: Implementation :: CPython
Requires-Python: >=3.7
License-File: LICENSE
Requires-Dist: ftd2xx
Provides-Extra: docs
Requires-Dist: psychopy; extra == "docs"
Requires-Dist: sphinx; extra == "docs"
Requires-Dist: furo; extra == "docs"
Provides-Extra: tests
Requires-Dist: psychopy; extra == "tests"
Requires-Dist: pytest; extra == "tests"
Dynamic: license-file
